{"otherData": {},"traceEvents":[{"cat":"function","dur":37730,"name":"glfwInit","ph":"X","pid":0,"tid":4185575291,"ts":26128025239},{"cat":"function","dur":246109,"name":"glfwCreateWindow","ph":"X","pid":0,"tid":4185575291,"ts":26128063115},{"cat":"function","dur":3323,"name":"void __cdecl miosGE::OpenGLContext::Init(void)","ph":"X","pid":0,"tid":4185575291,"ts":26128309300},{"cat":"function","dur":23,"name":"void __cdecl miosGE::WindowsWindow::SetVSync(bool)","ph":"X","pid":0,"tid":4185575291,"ts":26128312677},{"cat":"function","dur":288727,"name":"void __cdecl miosGE::WindowsWindow::Init(const struct miosGE::WindowsProps &)","ph":"X","pid":0,"tid":4185575291,"ts":26128024003},{"cat":"function","dur":288748,"name":"__cdecl miosGE::WindowsWindow::WindowsWindow(const struct miosGE::WindowsProps &)","ph":"X","pid":0,"tid":4185575291,"ts":26128024002},{"cat":"function","dur":5,"name":"void __cdecl miosGE::OpenGLRendererAPI::Init(void)","ph":"X","pid":0,"tid":4185575291,"ts":26128312786},{"cat":"function","dur":22,"name":"__cdecl miosGE::OpenGLVertexArray::OpenGLVertexArray(void)","ph":"X","pid":0,"tid":4185575291,"ts":26128312823},{"cat":"function","dur":51,"name":"class std::shared_ptr<class miosGE::VertexArray> __cdecl miosGE::VertexArray::Create(void)","ph":"X","pid":0,"tid":4185575291,"ts":26128312814},{"cat":"function","dur":15,"name":"__cdecl miosGE::OpenGLVertexBuffer::OpenGLVertexBuffer(unsigned int)","ph":"X","pid":0,"tid":4185575291,"ts":26128312899},{"cat":"function","dur":0,"name":"void __cdecl miosGE::OpenGLVertexBuffer::Bind(void) const","ph":"X","pid":0,"tid":4185575291,"ts":26128312998},{"cat":"function","dur":70,"name":"void __cdecl miosGE::OpenGLVertexArray::AddVertexBuffer(const class std::shared_ptr<class miosGE::VertexBuffer> &)","ph":"X","pid":0,"tid":4185575291,"ts":26128312957},{"cat":"function","dur":435,"name":"__cdecl miosGE::OpenGLIndexBuffer::OpenGLIndexBuffer(unsigned int *,unsigned int)","ph":"X","pid":0,"tid":4185575291,"ts":26128313918},{"cat":"function","dur":1,"name":"void __cdecl miosGE::OpenGLIndexBuffer::Bind(void) const","ph":"X","pid":0,"tid":4185575291,"ts":26128314384},{"cat":"function","dur":20,"name":"void __cdecl miosGE::OpenGLVertexArray::SetIndexBuffer(const class std::shared_ptr<class miosGE::IndexBuffer> &)","ph":"X","pid":0,"tid":4185575291,"ts":26128314384},{"cat":"function","dur":63,"name":"__cdecl miosGE::OpenGLTexture2D::OpenGLTexture2D(unsigned int,unsigned int)","ph":"X","pid":0,"tid":4185575291,"ts":26128314490},{"cat":"function","dur":9,"name":"void __cdecl miosGE::OpenGLTexture2D::SetData(void *,unsigned int)","ph":"X","pid":0,"tid":4185575291,"ts":26128314586},{"cat":"function","dur":155,"name":"class std::basic_string<char,struct std::char_traits<char>,class std::allocator<char> > __cdecl miosGE::OpenGLShader::ReadFile(const class std::basic_string<char,struct std::char_traits<char>,class std::allocator<char> > &)","ph":"X","pid":0,"tid":4185575291,"ts":26128314659},{"cat":"function","dur":33,"name":"class std::unordered_map<unsigned int,class std::basic_string<char,struct std::char_traits<char>,class std::allocator<char> >,struct std::hash<unsigned int>,struct std::equal_to<unsigned int>,class std::allocator<struct std::pair<unsigned int const ,class std::basic_string<char,struct std::char_traits<char>,class std::allocator<char> > > > > __cdecl miosGE::OpenGLShader::PreProcess(const class std::basic_string<char,struct std::char_traits<char>,class std::allocator<char> > &)","ph":"X","pid":0,"tid":4185575291,"ts":26128314839},{"cat":"function","dur":708,"name":"void __cdecl miosGE::OpenGLShader::Compile(const class std::unordered_map<unsigned int,class std::basic_string<char,struct std::char_traits<char>,class std::allocator<char> >,struct std::hash<unsigned int>,struct std::equal_to<unsigned int>,class std::allocator<struct std::pair<unsigned int const ,class std::basic_string<char,struct std::char_traits<char>,class std::allocator<char> > > > > &)","ph":"X","pid":0,"tid":4185575291,"ts":26128314897},{"cat":"function","dur":987,"name":"__cdecl miosGE::OpenGLShader::OpenGLShader(const class std::basic_string<char,struct std::char_traits<char>,class std::allocator<char> > &)","ph":"X","pid":0,"tid":4185575291,"ts":26128314658},{"cat":"function","dur":2,"name":"void __cdecl miosGE::OpenGLShader::Bind(void) const","ph":"X","pid":0,"tid":4185575291,"ts":26128315698},{"cat":"function","dur":76,"name":"void __cdecl miosGE::OpenGLShader::SetIntArray(const class std::basic_string<char,struct std::char_traits<char>,class std::allocator<char> > &,int *,unsigned int)","ph":"X","pid":0,"tid":4185575291,"ts":26128315724},{"cat":"function","dur":3018,"name":"void __cdecl miosGE::Renderer2D::Init(void)","ph":"X","pid":0,"tid":4185575291,"ts":26128312813},{"cat":"function","dur":3069,"name":"void __cdecl miosGE::Renderer::Init(void)","ph":"X","pid":0,"tid":4185575291,"ts":26128312783},{"cat":"function","dur":851,"name":"void __cdecl miosGE::ImGuiLayer::OnAttach(void)","ph":"X","pid":0,"tid":4185575291,"ts":26128315879},{"cat":"function","dur":881,"name":"void __cdecl miosGE::Application::PushOverlay(class miosGE::Layer *)","ph":"X","pid":0,"tid":4185575291,"ts":26128315876},{"cat":"function","dur":292784,"name":"__cdecl miosGE::Application::Application(const class std::basic_string<char,struct std::char_traits<char>,class std::allocator<char> > &)","ph":"X","pid":0,"tid":4185575291,"ts":26128023992},{"cat":"function","dur":2,"name":"__cdecl miosGE::OrthographicCamera::OrthographicCamera(float,float,float,float)","ph":"X","pid":0,"tid":4185575291,"ts":26128316802},{"cat":"function","dur":152,"name":"stbi_load - OpenGLTexture2D::OpenGLTexture2D(const std::string&)","ph":"X","pid":0,"tid":4185575291,"ts":26128316835},{"cat":"function","dur":195,"name":"__cdecl miosGE::OpenGLTexture2D::OpenGLTexture2D(const class std::basic_string<char,struct std::char_traits<char>,class std::allocator<char> > &)","ph":"X","pid":0,"tid":4185575291,"ts":26128316833},{"cat":"function","dur":1752,"name":"void __cdecl miosGE::EditorLayer::OnAttach(void)","ph":"X","pid":0,"tid":4185575291,"ts":26128316828},{"cat":"function","dur":1818,"name":"void __cdecl miosGE::Application::PushLayer(class miosGE::Layer *)","ph":"X","pid":0,"tid":4185575291,"ts":26128316823}]}